encrypt_decrypt/__init__.py
encrypt_decrypt/aes_encryptor.py
encrypt_decrypt/models.py
encrypt_decrypt/migrations/0001_initial.py
encrypt_decrypt/migrations/__init__.py
endecryption-0.0.2.dist-info/METADATA
endecryption-0.0.2.dist-info/WHEEL
endecryption-0.0.2.dist-info/top_level.txt
endecryption-0.0.2.dist-info/RECORD
